aioexponent/__init__.py
aioexponent/exceptions.py
aioexponent-0.5.2.dist-info/LICENSE
aioexponent-0.5.2.dist-info/METADATA
aioexponent-0.5.2.dist-info/WHEEL
aioexponent-0.5.2.dist-info/top_level.txt
aioexponent-0.5.2.dist-info/zip-safe
aioexponent-0.5.2.dist-info/RECORD
