Metadata-Version: 2.1
Name: aioexponent
Version: 0.5.2
Summary: Expo Server SDK for Python Asyncio
Home-page: https://github.com/Chefclub/expo-server-sdk-asyncio
Author: Expo Team
Author-email: exponent.team@gmail.com
License: MIT
Platform: UNKNOWN
Requires-Dist: aiohttp
